{
  "resourceType": "StructureDefinition",
  "id": "cpg-condition",
  "url": "http://hl7.org/fhir/uv/cpg/StructureDefinition/cpg-condition",
  "name": "CPGCondition",
  "title": "CPG Condition",
  "status": "active",
  "experimental": false,
  "description": "CPG condition represents the minimum expectations for communicating condition/problem information as part of a CPG case",
  "fhirVersion": "4.0.1",
  "mapping": [
    {
      "identity": "workflow",
      "uri": "http://hl7.org/fhir/workflow",
      "name": "Workflow Pattern"
    },
    {
      "identity": "sct-concept",
      "uri": "http://snomed.info/conceptdomain",
      "name": "SNOMED CT Concept Domain Binding"
    },
    {
      "identity": "v2",
      "uri": "http://hl7.org/v2",
      "name": "HL7 v2 Mapping"
    },
    {
      "identity": "rim",
      "uri": "http://hl7.org/v3",
      "name": "RIM Mapping"
    },
    {
      "identity": "w5",
      "uri": "http://hl7.org/fhir/fivews",
      "name": "FiveWs Pattern Mapping"
    },
    {
      "identity": "sct-attr",
      "uri": "http://snomed.org/attributebinding",
      "name": "SNOMED CT Attribute Binding"
    }
  ],
  "kind": "resource",
  "abstract": false,
  "type": "Condition",
  "baseDefinition": "http://hl7.org/fhir/StructureDefinition/Condition",
  "derivation": "constraint",
  "differential": {
    "element": [
      {
        "id": "Condition.extension",
        "path": "Condition.extension",
        "slicing": {
          "discriminator": [
            {
              "type": "value",
              "path": "url"
            }
          ],
          "ordered": false,
          "rules": "open"
        }
      },
      {
        "id": "Condition.extension:instantiatesCaseFeature",
        "path": "Condition.extension",
        "sliceName": "instantiatesCaseFeature",
        "min": 0,
        "max": "1",
        "type": [
          {
            "code": "Extension",
            "profile": [
              "http://hl7.org/fhir/uv/cpg/StructureDefinition/cpg-instantiatesCaseFeature"
            ]
          }
        ],
        "mustSupport": true
      },
      {
        "id": "Condition.extension:caseFeatureType",
        "path": "Condition.extension",
        "sliceName": "caseFeatureType",
        "min": 0,
        "max": "1",
        "type": [
          {
            "code": "Extension",
            "profile": [
              "http://hl7.org/fhir/uv/cpg/StructureDefinition/cpg-caseFeatureType"
            ]
          }
        ],
        "mustSupport": true
      },
      {
        "id": "Condition.extension:caseFeaturePertinence",
        "path": "Condition.extension",
        "sliceName": "caseFeaturePertinence",
        "min": 0,
        "max": "1",
        "type": [
          {
            "code": "Extension",
            "profile": [
              "http://hl7.org/fhir/uv/cpg/StructureDefinition/cpg-caseFeaturePertinence"
            ]
          }
        ],
        "mustSupport": true
      },
      {
        "id": "Condition.clinicalStatus",
        "path": "Condition.clinicalStatus",
        "mustSupport": true
      },
      {
        "id": "Condition.verificationStatus",
        "path": "Condition.verificationStatus",
        "mustSupport": true
      },
      {
        "id": "Condition.category",
        "path": "Condition.category",
        "min": 1
      },
      {
        "id": "Condition.code",
        "path": "Condition.code",
        "min": 1
      },
      {
        "id": "Condition.subject",
        "path": "Condition.subject",
        "type": [
          {
            "code": "Reference",
            "targetProfile": [
              "http://hl7.org/fhir/uv/cpg/StructureDefinition/cpg-patient"
            ]
          }
        ],
        "mustSupport": true
      },
      {
        "id": "Condition.encounter",
        "path": "Condition.encounter",
        "type": [
          {
            "code": "Reference",
            "targetProfile": [
              "http://hl7.org/fhir/uv/cpg/StructureDefinition/cpg-encounter"
            ]
          }
        ],
        "mustSupport": true
      },
      {
        "id": "Condition.onset[x]",
        "path": "Condition.onset[x]",
        "type": [
          {
            "code": "dateTime"
          },
          {
            "code": "Age"
          },
          {
            "code": "Period"
          },
          {
            "code": "Range"
          }
        ],
        "mustSupport": true
      },
      {
        "id": "Condition.abatement[x]",
        "path": "Condition.abatement[x]",
        "type": [
          {
            "code": "dateTime"
          },
          {
            "code": "Age"
          },
          {
            "code": "Period"
          },
          {
            "code": "Range"
          }
        ],
        "mustSupport": true
      },
      {
        "id": "Condition.evidence",
        "path": "Condition.evidence",
        "mustSupport": true
      },
      {
        "id": "Condition.evidence.code",
        "path": "Condition.evidence.code",
        "mustSupport": true
      },
      {
        "id": "Condition.evidence.detail",
        "path": "Condition.evidence.detail",
        "mustSupport": true
      }
    ]
  }
}
