{
  "resourceType": "StructureDefinition",
  "id": "cpg-publishableguideline",
  "url": "http://hl7.org/fhir/uv/cpg/StructureDefinition/cpg-publishableguideline",
  "name": "CPGPublishableGuideline",
  "title": "CPG Publishable Guideline",
  "status": "active",
  "experimental": false,
  "description": "Profile of ImplementationGuide to describe the minimum expectations for a publishable Clinical Practice Guideline",
  "fhirVersion": "4.0.1",
  "mapping": [
    {
      "identity": "rim",
      "uri": "http://hl7.org/v3",
      "name": "RIM Mapping"
    },
    {
      "identity": "workflow",
      "uri": "http://hl7.org/fhir/workflow",
      "name": "Workflow Pattern"
    },
    {
      "identity": "w5",
      "uri": "http://hl7.org/fhir/fivews",
      "name": "FiveWs Pattern Mapping"
    },
    {
      "identity": "objimpl",
      "uri": "http://hl7.org/fhir/object-implementation",
      "name": "Object Implementation Information"
    }
  ],
  "kind": "resource",
  "abstract": false,
  "type": "ImplementationGuide",
  "baseDefinition": "http://hl7.org/fhir/uv/cpg/StructureDefinition/cpg-shareableig",
  "derivation": "constraint",
  "differential": {
    "element": [
      {
        "id": "ImplementationGuide.extension:approvalDate",
        "path": "ImplementationGuide.extension",
        "sliceName": "approvalDate",
        "min": 0,
        "max": "1",
        "type": [
          {
            "code": "Extension",
            "profile": [
              "http://hl7.org/fhir/StructureDefinition/resource-approvalDate"
            ]
          }
        ],
        "mustSupport": true
      },
      {
        "id": "ImplementationGuide.extension:effectivePeriod",
        "path": "ImplementationGuide.extension",
        "sliceName": "effectivePeriod",
        "min": 0,
        "max": "1",
        "type": [
          {
            "code": "Extension",
            "profile": [
              "http://hl7.org/fhir/StructureDefinition/resource-effectivePeriod"
            ]
          }
        ],
        "mustSupport": true
      },
      {
        "id": "ImplementationGuide.extension:lastReviewDate",
        "path": "ImplementationGuide.extension",
        "sliceName": "lastReviewDate",
        "min": 0,
        "max": "1",
        "type": [
          {
            "code": "Extension",
            "profile": [
              "http://hl7.org/fhir/StructureDefinition/resource-lastReviewDate"
            ]
          }
        ],
        "mustSupport": true
      },
      {
        "id": "ImplementationGuide.extension:topic",
        "path": "ImplementationGuide.extension",
        "sliceName": "topic",
        "min": 0,
        "max": "*",
        "type": [
          {
            "code": "Extension",
            "profile": [
              "http://hl7.org/fhir/uv/cpg/StructureDefinition/cpg-topic"
            ]
          }
        ]
      },
      {
        "id": "ImplementationGuide.extension:author",
        "path": "ImplementationGuide.extension",
        "sliceName": "author",
        "min": 0,
        "max": "*",
        "type": [
          {
            "code": "Extension",
            "profile": [
              "http://hl7.org/fhir/uv/cpg/StructureDefinition/cpg-author"
            ]
          }
        ]
      },
      {
        "id": "ImplementationGuide.extension:editor",
        "path": "ImplementationGuide.extension",
        "sliceName": "editor",
        "min": 0,
        "max": "*",
        "type": [
          {
            "code": "Extension",
            "profile": [
              "http://hl7.org/fhir/uv/cpg/StructureDefinition/cpg-editor"
            ]
          }
        ]
      },
      {
        "id": "ImplementationGuide.extension:reviewer",
        "path": "ImplementationGuide.extension",
        "sliceName": "reviewer",
        "min": 0,
        "max": "*",
        "type": [
          {
            "code": "Extension",
            "profile": [
              "http://hl7.org/fhir/uv/cpg/StructureDefinition/cpg-reviewer"
            ]
          }
        ]
      },
      {
        "id": "ImplementationGuide.extension:endorser",
        "path": "ImplementationGuide.extension",
        "sliceName": "endorser",
        "min": 0,
        "max": "*",
        "type": [
          {
            "code": "Extension",
            "profile": [
              "http://hl7.org/fhir/uv/cpg/StructureDefinition/cpg-endorser"
            ]
          }
        ]
      },
      {
        "id": "ImplementationGuide.extension:relatedArtifact",
        "path": "ImplementationGuide.extension",
        "sliceName": "relatedArtifact",
        "min": 0,
        "max": "*",
        "type": [
          {
            "code": "Extension",
            "profile": [
              "http://hl7.org/fhir/uv/cpg/StructureDefinition/cpg-relatedArtifact"
            ]
          }
        ],
        "mustSupport": true
      },
      {
        "id": "ImplementationGuide.copyright",
        "path": "ImplementationGuide.copyright",
        "mustSupport": true
      },
      {
        "id": "ImplementationGuide.license",
        "path": "ImplementationGuide.license",
        "mustSupport": true
      }
    ]
  }
}
